icinga2_passive_replicator/__init__.py
icinga2_passive_replicator/__main__.py
icinga2_passive_replicator/connection.py
icinga2_passive_replicator/containers.py
icinga2_passive_replicator/routes.py
icinga2_passive_replicator/sink_connection.py
icinga2_passive_replicator/source_connection.py
icinga2_passive_replicator-0.1.0.dist-info/COPYING
icinga2_passive_replicator-0.1.0.dist-info/LICENSE
icinga2_passive_replicator-0.1.0.dist-info/METADATA
icinga2_passive_replicator-0.1.0.dist-info/WHEEL
icinga2_passive_replicator-0.1.0.dist-info/top_level.txt
icinga2_passive_replicator-0.1.0.dist-info/RECORD
