Metadata-Version: 2.1
Name: icinga2-passive-replicator
Version: 0.1.0
Summary: A Icinga2 to Icinga2 replicator using passive checks
Home-page: https://github.com/opsdis/icinga2-passive-replicator
Author: thenodon
Author-email: anders@opsdis.com
License: GPLv3
Platform: UNKNOWN
Requires-Python: >=3.8
License-File: LICENSE
License-File: COPYING
Requires-Dist: fastapi (==0.70.1)
Requires-Dist: fastapi-utils (==0.2.1)
Requires-Dist: uvicorn (==0.17.6)
Requires-Dist: requests (==2.27.1)
Requires-Dist: pydantic (==1.9.0)
Requires-Dist: python-dotenv (==0.20.0)
Requires-Dist: urllib3 (~=1.26.7)
